invariant_causal_prediction/__init__.py
invariant_causal_prediction/_version.py
invariant_causal_prediction/hidden_icp.py
invariant_causal_prediction/icp.py
invariant_causal_prediction/summary.py
invariant_causal_prediction/viz.py
invariant_causal_prediction/tests/test_parity_with_r.py
invariant_causal_prediction/tests/test_smoke.py
invariant_causal_prediction-0.1.1.dist-info/licenses/LICENSE
invariant_causal_prediction-0.1.1.dist-info/METADATA
invariant_causal_prediction-0.1.1.dist-info/WHEEL
invariant_causal_prediction-0.1.1.dist-info/top_level.txt
invariant_causal_prediction-0.1.1.dist-info/RECORD
