Metadata-Version: 2.4
Name: invariant-causal-prediction
Version: 0.1.1
Summary: Invariant Causal Prediction (ICP) for Python: causal predictor discovery via invariance across environments with confidence intervals and R-parity tests.
Author-email: Simon Zimmermann <simon.zimmermann@arc-intelligence.de>
License: GNU GENERAL PUBLIC LICENSE
Project-URL: Homepage, https://github.com/simzim96/invariant_causal_prediction
Project-URL: Repository, https://github.com/simzim96/invariant_causal_prediction
Project-URL: Issues, https://github.com/simzim96/invariant_causal_prediction/issues
Keywords: causal-inference,invariant-causal-prediction,icp,statistics,machine-learning,robustness
Classifier: Development Status :: 3 - Alpha
Classifier: Intended Audience :: Science/Research
Classifier: License :: OSI Approved :: GNU General Public License v2 or later (GPLv2+)
Classifier: Programming Language :: Python :: 3
Classifier: Programming Language :: Python :: 3.9
Classifier: Programming Language :: Python :: 3.10
Classifier: Programming Language :: Python :: 3.11
Classifier: Programming Language :: Python :: 3.12
Classifier: Topic :: Scientific/Engineering
Classifier: Topic :: Scientific/Engineering :: Information Analysis
Requires-Python: >=3.9
License-File: LICENSE
Requires-Dist: numpy>=1.23
Requires-Dist: scipy>=1.9
Requires-Dist: scikit-learn>=1.1
Requires-Dist: pandas>=1.5
Requires-Dist: statsmodels>=0.14
Requires-Dist: matplotlib>=3.7
Dynamic: license-file
